Metadata-Version: 2.1
Name: aminolib
Version: 0.0.7
Summary: Library for Amino
Home-page: https://github.com/EpicSans002/aminolib
Author: @kingzero#6580
License: MIT
Project-URL: aminolib, https://github.com/EpicSans002/aminolib/issues
Keywords: amino,aminolib,Lord,AminoAPI
Platform: UNKNOWN
Classifier: Programming Language :: Python :: 3
Classifier: License :: OSI Approved :: MIT License
Classifier: Operating System :: OS Independent
Requires-Python: >=3.6
License-File: LICENSE
